Workbook

Sheet Read Me
A1: Commission Cash-Flow Model
A2: Broker Financial Toolkit · Wealth Building Broker · 2026 Edition
A5: Why this model exists: | B5: A commission check is not income. It's gross revenue that has to survive your franchise royalty, your split, your cap, transaction fees, taxes, and your own spending habits before any of it is yours. This model makes every dollar's path visible.
A7: 1. Settings | B7: Your split, cap, royalty, fees, and allocation percentages. Set once, adjust as your contract changes.
A8: 2. Commission Log | B8: Log every closing. The model tracks your cap and royalty cap AUTOMATICALLY — once you cap, the math changes on its own.
A9: 3. Dashboard | B9: YTD totals: what you grossed, what the brokerage kept, what the IRS is owed, and what was actually yours.
A10: 4. Check Calculator | B10: Before you spend a pending commission, see what it's really worth.
A12: The allocation system (Profit First for agents): | B12: Every net commission is split by fixed percentages the day it lands: Tax set-aside → tax account. Profit → untouchable. Owner pay → what you live on. Operating → business costs. If you only adopt one habit from this toolkit, make it this one.
A14: Blue cells are yours. Black cells are formulas. Yellow cells are worth reviewing once.
A16: Educational tool only — not tax, legal, or investment advice. Verify all figures with your CPA. Lance Hulsey, CA Real Estate Broker, DRE# 01724888 · wealthbuildingbroker.com

Sheet Settings
A1: Your Brokerage & Allocation Settings
A2: Defaults show a common KW-style structure — replace with YOUR contract numbers.
A4: BROKERAGE STRUCTURE
A5: Broker split (their share of GCI, pre-cap) | B5: 0.3 | C5: e.g., 70/30 split = 30% to broker
A6: Company-dollar cap (annual) | B6: 16000 | C6: Once the broker has kept this much, you go to 100%
A7: Franchise royalty rate | B7: 0.06 | C7: KW: 6% of GCI
A8: Franchise royalty cap (annual) | B8: 3000 | C8: KW: $3,000/anniversary year
A9: Flat transaction/E&O fee per closing | B9: 150 | C9: Whatever your brokerage charges per file
A11: ALLOCATION OF EVERY NET COMMISSION
A12: Tax set-aside | B12: 0.3 | C12: 30% is the CA-agent starting point; tune with the Quarterly Tax Planner
A13: Profit (untouchable) | B13: 0.05 | C13: Pay yourself first — this is how the down-payment fund grows
A14: Owner pay (what you live on) | B14: 0.5
A15: Operating (business expenses) | B15: 0.15
A16: Allocation check (must equal 100%) | B16: =B12+B13+B14+B15 -> 1
A18: Educational tool only — not tax, legal, or investment advice. Verify all figures with your CPA. Lance Hulsey, CA Real Estate Broker, DRE# 01724888 · wealthbuildingbroker.com

Sheet Commission Log
A1: Commission Log — cap-aware
A2: Log each closing. Columns F-G handle your royalty cap and company-dollar cap automatically.
A4: Close Date | B4: Property / Client | C4: Sale Price | D4: GCI % | E4: GCI | F4: Royalty (capped) | G4: Company Dollar (capped) | H4: Txn Fee | I4: Net Commission | J4: → Tax | K4: → Profit | L4: → Owner Pay | M4: → Operating | N4: Cap Used YTD
A5: 1/15/2026 | B5: 123 Ocean View Dr — Buyer | C5: 950000 | D5: 0.025 | E5: =IF($C5="","",$C5*$D5) -> 23750 | F5: =IF($C5="","",MAX(0,MIN(Settings!$B$7*E5,Settings!$B$8-0))) -> 1425 | G5: =IF($C5="","",MAX(0,MIN(Settings!$B$5*E5,Settings!$B$6-0))) -> 7125 | H5: =IF($C5="","",Settings!$B$9) -> 150 | I5: =IF($C5="","",E5-F5-G5-H5) -> 15050 | J5: =IF($C5="","",$I5*Settings!$B$12) -> 4515 | K5: =IF($C5="","",$I5*Settings!$B$13) -> 752.5 | L5: =IF($C5="","",$I5*Settings!$B$14) -> 7525 | M5: =IF($C5="","",$I5*Settings!$B$15) -> 2257.5 | N5: =IF($C5="","",SUM(G$5:G5)) -> 7125
A6: 2/28/2026 | B6: 47 Redwood Ln — Seller | C6: 1250000 | D6: 0.025 | E6: =IF($C6="","",$C6*$D6) -> 31250 | F6: =IF($C6="","",MAX(0,MIN(Settings!$B$7*E6,Settings!$B$8-SUM(F$5:F5)))) -> 1575 | G6: =IF($C6="","",MAX(0,MIN(Settings!$B$5*E6,Settings!$B$6-SUM(G$5:G5)))) -> 8875 | H6: =IF($C6="","",Settings!$B$9) -> 150 | I6: =IF($C6="","",E6-F6-G6-H6) -> 20650 | J6: =IF($C6="","",$I6*Settings!$B$12) -> 6195 | K6: =IF($C6="","",$I6*Settings!$B$13) -> 1032.5 | L6: =IF($C6="","",$I6*Settings!$B$14) -> 10325 | M6: =IF($C6="","",$I6*Settings!$B$15) -> 3097.5 | N6: =IF($C6="","",SUM(G$5:G6)) -> 16000
A7: 4/10/2026 | B7: 882 Soquel Ave — Buyer | C7: 760000 | D7: 0.03 | E7: =IF($C7="","",$C7*$D7) -> 22800 | F7: =IF($C7="","",MAX(0,MIN(Settings!$B$7*E7,Settings!$B$8-SUM(F$5:F6)))) -> 0 | G7: =IF($C7="","",MAX(0,MIN(Settings!$B$5*E7,Settings!$B$6-SUM(G$5:G6)))) -> 0 | H7: =IF($C7="","",Settings!$B$9) -> 150 | I7: =IF($C7="","",E7-F7-G7-H7) -> 22650 | J7: =IF($C7="","",$I7*Settings!$B$12) -> 6795 | K7: =IF($C7="","",$I7*Settings!$B$13) -> 1132.5 | L7: =IF($C7="","",$I7*Settings!$B$14) -> 11325 | M7: =IF($C7="","",$I7*Settings!$B$15) -> 3397.5 | N7: =IF($C7="","",SUM(G$5:G7)) -> 16000
E8: =IF($C8="","",$C8*$D8) | F8: =IF($C8="","",MAX(0,MIN(Settings!$B$7*E8,Settings!$B$8-SUM(F$5:F7)))) | G8: =IF($C8="","",MAX(0,MIN(Settings!$B$5*E8,Settings!$B$6-SUM(G$5:G7)))) | H8: =IF($C8="","",Settings!$B$9) | I8: =IF($C8="","",E8-F8-G8-H8) | J8: =IF($C8="","",$I8*Settings!$B$12) | K8: =IF($C8="","",$I8*Settings!$B$13) | L8: =IF($C8="","",$I8*Settings!$B$14) | M8: =IF($C8="","",$I8*Settings!$B$15) | N8: =IF($C8="","",SUM(G$5:G8))
E9: =IF($C9="","",$C9*$D9) | F9: =IF($C9="","",MAX(0,MIN(Settings!$B$7*E9,Settings!$B$8-SUM(F$5:F8)))) | G9: =IF($C9="","",MAX(0,MIN(Settings!$B$5*E9,Settings!$B$6-SUM(G$5:G8)))) | H9: =IF($C9="","",Settings!$B$9) | I9: =IF($C9="","",E9-F9-G9-H9) | J9: =IF($C9="","",$I9*Settings!$B$12) | K9: =IF($C9="","",$I9*Settings!$B$13) | L9: =IF($C9="","",$I9*Settings!$B$14) | M9: =IF($C9="","",$I9*Settings!$B$15) | N9: =IF($C9="","",SUM(G$5:G9))
E10: =IF($C10="","",$C10*$D10) | F10: =IF($C10="","",MAX(0,MIN(Settings!$B$7*E10,Settings!$B$8-SUM(F$5:F9)))) | G10: =IF($C10="","",MAX(0,MIN(Settings!$B$5*E10,Settings!$B$6-SUM(G$5:G9)))) | H10: =IF($C10="","",Settings!$B$9) | I10: =IF($C10="","",E10-F10-G10-H10) | J10: =IF($C10="","",$I10*Settings!$B$12) | K10: =IF($C10="","",$I10*Settings!$B$13) | L10: =IF($C10="","",$I10*Settings!$B$14) | M10: =IF($C10="","",$I10*Settings!$B$15) | N10: =IF($C10="","",SUM(G$5:G10))
E11: =IF($C11="","",$C11*$D11) | F11: =IF($C11="","",MAX(0,MIN(Settings!$B$7*E11,Settings!$B$8-SUM(F$5:F10)))) | G11: =IF($C11="","",MAX(0,MIN(Settings!$B$5*E11,Settings!$B$6-SUM(G$5:G10)))) | H11: =IF($C11="","",Settings!$B$9) | I11: =IF($C11="","",E11-F11-G11-H11) | J11: =IF($C11="","",$I11*Settings!$B$12) | K11: =IF($C11="","",$I11*Settings!$B$13) | L11: =IF($C11="","",$I11*Settings!$B$14) | M11: =IF($C11="","",$I11*Settings!$B$15) | N11: =IF($C11="","",SUM(G$5:G11))
E12: =IF($C12="","",$C12*$D12) | F12: =IF($C12="","",MAX(0,MIN(Settings!$B$7*E12,Settings!$B$8-SUM(F$5:F11)))) | G12: =IF($C12="","",MAX(0,MIN(Settings!$B$5*E12,Settings!$B$6-SUM(G$5:G11)))) | H12: =IF($C12="","",Settings!$B$9) | I12: =IF($C12="","",E12-F12-G12-H12) | J12: =IF($C12="","",$I12*Settings!$B$12) | K12: =IF($C12="","",$I12*Settings!$B$13) | L12: =IF($C12="","",$I12*Settings!$B$14) | M12: =IF($C12="","",$I12*Settings!$B$15) | N12: =IF($C12="","",SUM(G$5:G12))
E13: =IF($C13="","",$C13*$D13) | F13: =IF($C13="","",MAX(0,MIN(Settings!$B$7*E13,Settings!$B$8-SUM(F$5:F12)))) | G13: =IF($C13="","",MAX(0,MIN(Settings!$B$5*E13,Settings!$B$6-SUM(G$5:G12)))) | H13: =IF($C13="","",Settings!$B$9) | I13: =IF($C13="","",E13-F13-G13-H13) | J13: =IF($C13="","",$I13*Settings!$B$12) | K13: =IF($C13="","",$I13*Settings!$B$13) | L13: =IF($C13="","",$I13*Settings!$B$14) | M13: =IF($C13="","",$I13*Settings!$B$15) | N13: =IF($C13="","",SUM(G$5:G13))
E14: =IF($C14="","",$C14*$D14) | F14: =IF($C14="","",MAX(0,MIN(Settings!$B$7*E14,Settings!$B$8-SUM(F$5:F13)))) | G14: =IF($C14="","",MAX(0,MIN(Settings!$B$5*E14,Settings!$B$6-SUM(G$5:G13)))) | H14: =IF($C14="","",Settings!$B$9) | I14: =IF($C14="","",E14-F14-G14-H14) | J14: =IF($C14="","",$I14*Settings!$B$12) | K14: =IF($C14="","",$I14*Settings!$B$13) | L14: =IF($C14="","",$I14*Settings!$B$14) | M14: =IF($C14="","",$I14*Settings!$B$15) | N14: =IF($C14="","",SUM(G$5:G14))
E15: =IF($C15="","",$C15*$D15) | F15: =IF($C15="","",MAX(0,MIN(Settings!$B$7*E15,Settings!$B$8-SUM(F$5:F14)))) | G15: =IF($C15="","",MAX(0,MIN(Settings!$B$5*E15,Settings!$B$6-SUM(G$5:G14)))) | H15: =IF($C15="","",Settings!$B$9) | I15: =IF($C15="","",E15-F15-G15-H15) | J15: =IF($C15="","",$I15*Settings!$B$12) | K15: =IF($C15="","",$I15*Settings!$B$13) | L15: =IF($C15="","",$I15*Settings!$B$14) | M15: =IF($C15="","",$I15*Settings!$B$15) | N15: =IF($C15="","",SUM(G$5:G15))
E16: =IF($C16="","",$C16*$D16) | F16: =IF($C16="","",MAX(0,MIN(Settings!$B$7*E16,Settings!$B$8-SUM(F$5:F15)))) | G16: =IF($C16="","",MAX(0,MIN(Settings!$B$5*E16,Settings!$B$6-SUM(G$5:G15)))) | H16: =IF($C16="","",Settings!$B$9) | I16: =IF($C16="","",E16-F16-G16-H16) | J16: =IF($C16="","",$I16*Settings!$B$12) | K16: =IF($C16="","",$I16*Settings!$B$13) | L16: =IF($C16="","",$I16*Settings!$B$14) | M16: =IF($C16="","",$I16*Settings!$B$15) | N16: =IF($C16="","",SUM(G$5:G16))
E17: =IF($C17="","",$C17*$D17) | F17: =IF($C17="","",MAX(0,MIN(Settings!$B$7*E17,Settings!$B$8-SUM(F$5:F16)))) | G17: =IF($C17="","",MAX(0,MIN(Settings!$B$5*E17,Settings!$B$6-SUM(G$5:G16)))) | H17: =IF($C17="","",Settings!$B$9) | I17: =IF($C17="","",E17-F17-G17-H17) | J17: =IF($C17="","",$I17*Settings!$B$12) | K17: =IF($C17="","",$I17*Settings!$B$13) | L17: =IF($C17="","",$I17*Settings!$B$14) | M17: =IF($C17="","",$I17*Settings!$B$15) | N17: =IF($C17="","",SUM(G$5:G17))
E18: =IF($C18="","",$C18*$D18) | F18: =IF($C18="","",MAX(0,MIN(Settings!$B$7*E18,Settings!$B$8-SUM(F$5:F17)))) | G18: =IF($C18="","",MAX(0,MIN(Settings!$B$5*E18,Settings!$B$6-SUM(G$5:G17)))) | H18: =IF($C18="","",Settings!$B$9) | I18: =IF($C18="","",E18-F18-G18-H18) | J18: =IF($C18="","",$I18*Settings!$B$12) | K18: =IF($C18="","",$I18*Settings!$B$13) | L18: =IF($C18="","",$I18*Settings!$B$14) | M18: =IF($C18="","",$I18*Settings!$B$15) | N18: =IF($C18="","",SUM(G$5:G18))
E19: =IF($C19="","",$C19*$D19) | F19: =IF($C19="","",MAX(0,MIN(Settings!$B$7*E19,Settings!$B$8-SUM(F$5:F18)))) | G19: =IF($C19="","",MAX(0,MIN(Settings!$B$5*E19,Settings!$B$6-SUM(G$5:G18)))) | H19: =IF($C19="","",Settings!$B$9) | I19: =IF($C19="","",E19-F19-G19-H19) | J19: =IF($C19="","",$I19*Settings!$B$12) | K19: =IF($C19="","",$I19*Settings!$B$13) | L19: =IF($C19="","",$I19*Settings!$B$14) | M19: =IF($C19="","",$I19*Settings!$B$15) | N19: =IF($C19="","",SUM(G$5:G19))
... E44: =IF($C44="","",$C44*$D44) | F44: =IF($C44="","",MAX(0,MIN(Settings!$B$7*E44,Settings!$B$8-SUM(F$5:F43)))) | G44: =IF($C44="","",MAX(0,MIN(Settings!$B$5*E44,Settings!$B$6-SUM(G$5:G43)))) | H44: =IF($C44="","",Settings!$B$9) | I44: =IF($C44="","",E44-F44-G44-H44) | J44: =IF($C44="","",$I44*Settings!$B$12) | K44: =IF($C44="","",$I44*Settings!$B$13) | L44: =IF($C44="","",$I44*Settings!$B$14) | M44: =IF($C44="","",$I44*Settings!$B$15) | N44: =IF($C44="","",SUM(G$5:G44))
A46: Educational tool only — not tax, legal, or investment advice. Verify all figures with your CPA. Lance Hulsey, CA Real Estate Broker, DRE# 01724888 · wealthbuildingbroker.com

Sheet Dashboard
A1: Year-to-Date Dashboard
A2: Everything below sums automatically from the Commission Log.
A4: PRODUCTION
A5: Closings YTD | B5: =COUNT('Commission Log'!C5:C44) -> 3
A6: Volume YTD | B6: =SUM('Commission Log'!C5:C44) -> 2960000
A7: GCI YTD | B7: =SUM('Commission Log'!E5:E44) -> 77800
A9: WHERE IT WENT
A10: Franchise royalty paid | B10: =SUM('Commission Log'!F5:F44) -> 3000
A11: Company dollar paid (cap progress) | B11: =SUM('Commission Log'!G5:G44) -> 16000
A12: Cap remaining | B12: =MAX(0,Settings!B6-B11) -> 0 | C12: $0 means you've capped — congratulations
A13: Transaction fees | B13: =SUM('Commission Log'!H5:H44) -> 450
A14: Net commission income YTD | B14: =SUM('Commission Log'!I5:I44) -> 58350
A16: YOUR ALLOCATIONS
A17: Tax set-aside balance (should be in a separate account) | B17: =SUM('Commission Log'!J5:J44) -> 17505
A18: Profit accumulated | B18: =SUM('Commission Log'!K5:K44) -> 2917.5
A19: Owner pay YTD | B19: =SUM('Commission Log'!L5:L44) -> 29175
A20: Operating budget YTD | B20: =SUM('Commission Log'!M5:M44) -> 8752.5
A22: THE NUMBER THAT MATTERS
A23: Take-home rate (owner pay + profit as % of GCI) | B23: =IF(B7=0,"",(B18+B19)/B7) -> 0.4125 | C23: Most agents guess 70-80%. Reality is usually 45-55%. Now you know yours.
A25: Educational tool only — not tax, legal, or investment advice. Verify all figures with your CPA. Lance Hulsey, CA Real Estate Broker, DRE# 01724888 · wealthbuildingbroker.com

Sheet Check Calculator
A1: What Is This Check Actually Worth?
A2: For the commission you haven't received yet. Uses your Settings.
A4: Sale price | B4: 850000
A5: Your commission % | B5: 0.025
A6: Have you already capped this year? (Y/N) | B6: N
A7: Royalty cap already met? (Y/N) | B7: N
A9: Gross commission (GCI) | B9: =B4*B5 -> 21250
A10: Less: franchise royalty | B10: =IF(UPPER(B7)="Y",0,-Settings!B7*B9) -> -1275
A11: Less: company dollar | B11: =IF(UPPER(B6)="Y",0,-Settings!B5*B9) -> -6375
A12: Less: transaction fee | B12: =-Settings!B9 -> -150
A13: Net commission | B13: =SUM(B9:B12) -> 13450
A14: Less: tax set-aside | B14: =-B13*Settings!B12 -> -4035
A15: Less: profit allocation | B15: =-B13*Settings!B13 -> -672.5
A16: Less: operating allocation | B16: =-B13*Settings!B15 -> -2017.5
A17: WHAT YOU CAN ACTUALLY SPEND | B17: =B13+B14+B15+B16 -> 6725
A19: Spendable as % of what the client thinks you made | B19: =IF(B9=0,"",B17/B9) -> 0.31647059
A21: Educational tool only — not tax, legal, or investment advice. Verify all figures with your CPA. Lance Hulsey, CA Real Estate Broker, DRE# 01724888 · wealthbuildingbroker.com
