Workbook

Sheet Read Me
A1: Entity Structure Decision Kit
A2: Broker Financial Toolkit · Wealth Building Broker · 2026 Edition
A5: What this kit does:
A6: 1. S-Corp Breakeven | B6: Models sole proprietor vs. S-corp at YOUR income, with real 2026 payroll tax numbers and California costs.
A7: 2. Breakeven Table | B7: Shows the savings (or cost) of an S-corp at every income level from $60K to $400K so you can see where the math flips.
A8: 3. Reasonable Comp | B8: Builds a defensible reasonable-compensation figure from what you actually do all week — the worksheet to bring to your CPA.
A9: 4. CPA Checklist | B9: The exact questions to ask before you convert. A 30-minute CPA meeting with this filled out beats a $2,000 exploratory engagement.
A11: How to use it:
A12: Blue cells | B12: Your inputs — change these.
A13: Yellow cells | B13: Key assumptions — review them once, they rarely change.
A14: Black cells | B14: Formulas — leave them alone.
A16: The one-sentence rule: | B16: If your net commission income (after expenses) is consistently above ~$60-80K, the S-corp conversation is worth having. This kit tells you how much it's worth.
A18: Educational tool only — not tax, legal, or investment advice. Verify all figures with your CPA. Lance Hulsey, CA Real Estate Broker, DRE# 01724888 · wealthbuildingbroker.com

Sheet S-Corp Breakeven
A1: Sole Prop vs. S-Corp — 2026 Breakeven Model
A2: All tax constants are 2026 federal + California figures. Sources noted in column E.
A4: YOUR INPUTS
A5: Net commission income (after business expenses, before owner pay) | B5: 150000 | E5: Your Schedule C net profit if you filed as a sole prop
A6: Reasonable compensation (W-2 salary you'd pay yourself) | B6: 80000 | E6: Use the Reasonable Comp sheet to build this number
A7: Annual payroll service + bookkeeping upgrade cost | B7: 2400 | E7: Gusto/ADP ~$60-100/mo + extra bookkeeping
A8: Additional tax-prep cost (1120-S + payroll filings) | B8: 1200 | E8: CPA delta vs. Schedule C return
A10: 2026 TAX CONSTANTS
A11: Social Security wage base (2026) | B11: 184500 | E11: Source: SSA.gov, 2026 contribution and benefit base
A12: SE income factor | B12: 0.9235 | E12: IRS Schedule SE — 92.35% of net SE income is taxable
A13: Social Security rate (combined) | B13: 0.124 | E13: 12.4% — employee+employer or SE
A14: Medicare rate (combined) | B14: 0.029 | E14: 2.9% on all earnings; +0.9% Addl Medicare over $200K single/$250K MFJ (not modeled)
A15: CA S-corp franchise tax rate | B15: 0.015 | E15: 1.5% of S-corp net income; $800 minimum. Source: FTB.ca.gov
A16: CA minimum franchise tax | B16: 800 | E16: Waived first year for new corporations
A18: SCENARIO A — SOLE PROPRIETOR
A19: SE taxable base (net income × 92.35%) | B19: =B5*B12 -> 138525
A20: Social Security portion | B20: =MIN(B19,B11)*B13 -> 17177.1
A21: Medicare portion | B21: =B19*B14 -> 4017.225
A22: Total self-employment tax | B22: =B20+B21 -> 21194.325
A24: SCENARIO B — S-CORP
A25: FICA on W-2 salary (both halves) | B25: =MIN(B6,B11)*(B13+B14) -> 12240 | E25: You pay both employee and employer halves
A26: S-corp profit subject to CA franchise tax | B26: =MAX(0,B5-B6-B25/2) -> 63880 | E26: Net income less salary and employer payroll taxes
A27: CA franchise tax (greater of 1.5% or $800) | B27: =MAX(B16,B26*B15) -> 958.2
A28: Payroll service + extra tax prep | B28: =B7+B8 -> 3600
A29: Total S-corp taxes + costs | B29: =B25+B27+B28 -> 16798.2
A31: THE VERDICT
A32: Annual savings with S-corp | B32: =B22-B29 -> 4396.125
A33: Verdict | B33: =IF(B32>2000,"S-corp likely worth it — confirm with your CPA",IF(B32>0,"Marginal — the admin burden may not justify it","Stay a sole prop for now")) -> S-corp likely worth it — confirm with your CPA
A35: Note: QBI interaction | B35: S-corp salary reduces your QBI deduction base. At higher incomes this partially offsets payroll-tax savings — ask your CPA to run both. QBI is permanent under OBBBA (2025).
A37: Educational tool only — not tax, legal, or investment advice. Verify all figures with your CPA. Lance Hulsey, CA Real Estate Broker, DRE# 01724888 · wealthbuildingbroker.com

Sheet Breakeven Table
A1: S-Corp Savings by Income Level
A2: Salary assumption below; all other constants from the Breakeven sheet.
A4: Salary as % of net income | B4: 0.45 | C4: Typical CPA guidance lands between 40-60% — adjust and watch the table
A5: Minimum salary floor | B5: 45000 | C5: Reasonable comp can't be token-low; floor keeps the model honest
A7: Net Income | B7: Salary Used | C7: Sole-Prop SE Tax | D7: S-Corp Taxes + Costs | E7: Annual S-Corp Savings | F7: Verdict
A8: 60000 | B8: =MAX($B$5,A8*$B$4) -> 45000 | C8: =MIN(A8*'S-Corp Breakeven'!$B$12,'S-Corp Breakeven'!$B$11)*'S-Corp Breakeven'!$B$13+A8*'S-Corp Breakeven'!$B$12*'S-Corp Breakeven'!$B$14 -> 8477.73 | D8: =MIN(B8,'S-Corp Breakeven'!$B$11)*('S-Corp Breakeven'!$B$13+'S-Corp Breakeven'!$B$14)+MAX('S-Corp Breakeven'!$B$16,MAX(0,A8-B8-MIN(B8,'S-Corp Breakeven'!$B$11)*('S-Corp Breakeven'!$B$13+'S-Corp Breakeven'!$B$14)/2)*'S-Corp Breakeven'!$B$15)+'S-Corp Breakeven'!$B$7+'S-Corp Breakeven'!$B$8 -> 11285 | E8: =C8-D8 -> -2807.27 | F8: =IF(E8>2000,"Convert",IF(E8>0,"Marginal","Stay sole prop")) -> Stay sole prop
A9: 80000 | B9: =MAX($B$5,A9*$B$4) -> 45000 | C9: =MIN(A9*'S-Corp Breakeven'!$B$12,'S-Corp Breakeven'!$B$11)*'S-Corp Breakeven'!$B$13+A9*'S-Corp Breakeven'!$B$12*'S-Corp Breakeven'!$B$14 -> 11303.64 | D9: =MIN(B9,'S-Corp Breakeven'!$B$11)*('S-Corp Breakeven'!$B$13+'S-Corp Breakeven'!$B$14)+MAX('S-Corp Breakeven'!$B$16,MAX(0,A9-B9-MIN(B9,'S-Corp Breakeven'!$B$11)*('S-Corp Breakeven'!$B$13+'S-Corp Breakeven'!$B$14)/2)*'S-Corp Breakeven'!$B$15)+'S-Corp Breakeven'!$B$7+'S-Corp Breakeven'!$B$8 -> 11285 | E9: =C9-D9 -> 18.64 | F9: =IF(E9>2000,"Convert",IF(E9>0,"Marginal","Stay sole prop")) -> Marginal
A10: 100000 | B10: =MAX($B$5,A10*$B$4) -> 45000 | C10: =MIN(A10*'S-Corp Breakeven'!$B$12,'S-Corp Breakeven'!$B$11)*'S-Corp Breakeven'!$B$13+A10*'S-Corp Breakeven'!$B$12*'S-Corp Breakeven'!$B$14 -> 14129.55 | D10: =MIN(B10,'S-Corp Breakeven'!$B$11)*('S-Corp Breakeven'!$B$13+'S-Corp Breakeven'!$B$14)+MAX('S-Corp Breakeven'!$B$16,MAX(0,A10-B10-MIN(B10,'S-Corp Breakeven'!$B$11)*('S-Corp Breakeven'!$B$13+'S-Corp Breakeven'!$B$14)/2)*'S-Corp Breakeven'!$B$15)+'S-Corp Breakeven'!$B$7+'S-Corp Breakeven'!$B$8 -> 11285 | E10: =C10-D10 -> 2844.55 | F10: =IF(E10>2000,"Convert",IF(E10>0,"Marginal","Stay sole prop")) -> Convert
A11: 120000 | B11: =MAX($B$5,A11*$B$4) -> 54000 | C11: =MIN(A11*'S-Corp Breakeven'!$B$12,'S-Corp Breakeven'!$B$11)*'S-Corp Breakeven'!$B$13+A11*'S-Corp Breakeven'!$B$12*'S-Corp Breakeven'!$B$14 -> 16955.46 | D11: =MIN(B11,'S-Corp Breakeven'!$B$11)*('S-Corp Breakeven'!$B$13+'S-Corp Breakeven'!$B$14)+MAX('S-Corp Breakeven'!$B$16,MAX(0,A11-B11-MIN(B11,'S-Corp Breakeven'!$B$11)*('S-Corp Breakeven'!$B$13+'S-Corp Breakeven'!$B$14)/2)*'S-Corp Breakeven'!$B$15)+'S-Corp Breakeven'!$B$7+'S-Corp Breakeven'!$B$8 -> 12790.035 | E11: =C11-D11 -> 4165.425 | F11: =IF(E11>2000,"Convert",IF(E11>0,"Marginal","Stay sole prop")) -> Convert
A12: 140000 | B12: =MAX($B$5,A12*$B$4) -> 63000 | C12: =MIN(A12*'S-Corp Breakeven'!$B$12,'S-Corp Breakeven'!$B$11)*'S-Corp Breakeven'!$B$13+A12*'S-Corp Breakeven'!$B$12*'S-Corp Breakeven'!$B$14 -> 19781.37 | D12: =MIN(B12,'S-Corp Breakeven'!$B$11)*('S-Corp Breakeven'!$B$13+'S-Corp Breakeven'!$B$14)+MAX('S-Corp Breakeven'!$B$16,MAX(0,A12-B12-MIN(B12,'S-Corp Breakeven'!$B$11)*('S-Corp Breakeven'!$B$13+'S-Corp Breakeven'!$B$14)/2)*'S-Corp Breakeven'!$B$15)+'S-Corp Breakeven'!$B$7+'S-Corp Breakeven'!$B$8 -> 14321.708 | E12: =C12-D12 -> 5459.6625 | F12: =IF(E12>2000,"Convert",IF(E12>0,"Marginal","Stay sole prop")) -> Convert
A13: 160000 | B13: =MAX($B$5,A13*$B$4) -> 72000 | C13: =MIN(A13*'S-Corp Breakeven'!$B$12,'S-Corp Breakeven'!$B$11)*'S-Corp Breakeven'!$B$13+A13*'S-Corp Breakeven'!$B$12*'S-Corp Breakeven'!$B$14 -> 22607.28 | D13: =MIN(B13,'S-Corp Breakeven'!$B$11)*('S-Corp Breakeven'!$B$13+'S-Corp Breakeven'!$B$14)+MAX('S-Corp Breakeven'!$B$16,MAX(0,A13-B13-MIN(B13,'S-Corp Breakeven'!$B$11)*('S-Corp Breakeven'!$B$13+'S-Corp Breakeven'!$B$14)/2)*'S-Corp Breakeven'!$B$15)+'S-Corp Breakeven'!$B$7+'S-Corp Breakeven'!$B$8 -> 15853.38 | E13: =C13-D13 -> 6753.9 | F13: =IF(E13>2000,"Convert",IF(E13>0,"Marginal","Stay sole prop")) -> Convert
A14: 180000 | B14: =MAX($B$5,A14*$B$4) -> 81000 | C14: =MIN(A14*'S-Corp Breakeven'!$B$12,'S-Corp Breakeven'!$B$11)*'S-Corp Breakeven'!$B$13+A14*'S-Corp Breakeven'!$B$12*'S-Corp Breakeven'!$B$14 -> 25433.19 | D14: =MIN(B14,'S-Corp Breakeven'!$B$11)*('S-Corp Breakeven'!$B$13+'S-Corp Breakeven'!$B$14)+MAX('S-Corp Breakeven'!$B$16,MAX(0,A14-B14-MIN(B14,'S-Corp Breakeven'!$B$11)*('S-Corp Breakeven'!$B$13+'S-Corp Breakeven'!$B$14)/2)*'S-Corp Breakeven'!$B$15)+'S-Corp Breakeven'!$B$7+'S-Corp Breakeven'!$B$8 -> 17385.053 | E14: =C14-D14 -> 8048.1375 | F14: =IF(E14>2000,"Convert",IF(E14>0,"Marginal","Stay sole prop")) -> Convert
A15: 200000 | B15: =MAX($B$5,A15*$B$4) -> 90000 | C15: =MIN(A15*'S-Corp Breakeven'!$B$12,'S-Corp Breakeven'!$B$11)*'S-Corp Breakeven'!$B$13+A15*'S-Corp Breakeven'!$B$12*'S-Corp Breakeven'!$B$14 -> 28234.3 | D15: =MIN(B15,'S-Corp Breakeven'!$B$11)*('S-Corp Breakeven'!$B$13+'S-Corp Breakeven'!$B$14)+MAX('S-Corp Breakeven'!$B$16,MAX(0,A15-B15-MIN(B15,'S-Corp Breakeven'!$B$11)*('S-Corp Breakeven'!$B$13+'S-Corp Breakeven'!$B$14)/2)*'S-Corp Breakeven'!$B$15)+'S-Corp Breakeven'!$B$7+'S-Corp Breakeven'!$B$8 -> 18916.725 | E15: =C15-D15 -> 9317.575 | F15: =IF(E15>2000,"Convert",IF(E15>0,"Marginal","Stay sole prop")) -> Convert
A16: 220000 | B16: =MAX($B$5,A16*$B$4) -> 99000 | C16: =MIN(A16*'S-Corp Breakeven'!$B$12,'S-Corp Breakeven'!$B$11)*'S-Corp Breakeven'!$B$13+A16*'S-Corp Breakeven'!$B$12*'S-Corp Breakeven'!$B$14 -> 28769.93 | D16: =MIN(B16,'S-Corp Breakeven'!$B$11)*('S-Corp Breakeven'!$B$13+'S-Corp Breakeven'!$B$14)+MAX('S-Corp Breakeven'!$B$16,MAX(0,A16-B16-MIN(B16,'S-Corp Breakeven'!$B$11)*('S-Corp Breakeven'!$B$13+'S-Corp Breakeven'!$B$14)/2)*'S-Corp Breakeven'!$B$15)+'S-Corp Breakeven'!$B$7+'S-Corp Breakeven'!$B$8 -> 20448.397 | E16: =C16-D16 -> 8321.5325 | F16: =IF(E16>2000,"Convert",IF(E16>0,"Marginal","Stay sole prop")) -> Convert
A17: 240000 | B17: =MAX($B$5,A17*$B$4) -> 108000 | C17: =MIN(A17*'S-Corp Breakeven'!$B$12,'S-Corp Breakeven'!$B$11)*'S-Corp Breakeven'!$B$13+A17*'S-Corp Breakeven'!$B$12*'S-Corp Breakeven'!$B$14 -> 29305.56 | D17: =MIN(B17,'S-Corp Breakeven'!$B$11)*('S-Corp Breakeven'!$B$13+'S-Corp Breakeven'!$B$14)+MAX('S-Corp Breakeven'!$B$16,MAX(0,A17-B17-MIN(B17,'S-Corp Breakeven'!$B$11)*('S-Corp Breakeven'!$B$13+'S-Corp Breakeven'!$B$14)/2)*'S-Corp Breakeven'!$B$15)+'S-Corp Breakeven'!$B$7+'S-Corp Breakeven'!$B$8 -> 21980.07 | E17: =C17-D17 -> 7325.49 | F17: =IF(E17>2000,"Convert",IF(E17>0,"Marginal","Stay sole prop")) -> Convert
A18: 260000 | B18: =MAX($B$5,A18*$B$4) -> 117000 | C18: =MIN(A18*'S-Corp Breakeven'!$B$12,'S-Corp Breakeven'!$B$11)*'S-Corp Breakeven'!$B$13+A18*'S-Corp Breakeven'!$B$12*'S-Corp Breakeven'!$B$14 -> 29841.19 | D18: =MIN(B18,'S-Corp Breakeven'!$B$11)*('S-Corp Breakeven'!$B$13+'S-Corp Breakeven'!$B$14)+MAX('S-Corp Breakeven'!$B$16,MAX(0,A18-B18-MIN(B18,'S-Corp Breakeven'!$B$11)*('S-Corp Breakeven'!$B$13+'S-Corp Breakeven'!$B$14)/2)*'S-Corp Breakeven'!$B$15)+'S-Corp Breakeven'!$B$7+'S-Corp Breakeven'!$B$8 -> 23511.743 | E18: =C18-D18 -> 6329.4475 | F18: =IF(E18>2000,"Convert",IF(E18>0,"Marginal","Stay sole prop")) -> Convert
A19: 280000 | B19: =MAX($B$5,A19*$B$4) -> 126000 | C19: =MIN(A19*'S-Corp Breakeven'!$B$12,'S-Corp Breakeven'!$B$11)*'S-Corp Breakeven'!$B$13+A19*'S-Corp Breakeven'!$B$12*'S-Corp Breakeven'!$B$14 -> 30376.82 | D19: =MIN(B19,'S-Corp Breakeven'!$B$11)*('S-Corp Breakeven'!$B$13+'S-Corp Breakeven'!$B$14)+MAX('S-Corp Breakeven'!$B$16,MAX(0,A19-B19-MIN(B19,'S-Corp Breakeven'!$B$11)*('S-Corp Breakeven'!$B$13+'S-Corp Breakeven'!$B$14)/2)*'S-Corp Breakeven'!$B$15)+'S-Corp Breakeven'!$B$7+'S-Corp Breakeven'!$B$8 -> 25043.415 | E19: =C19-D19 -> 5333.405 | F19: =IF(E19>2000,"Convert",IF(E19>0,"Marginal","Stay sole prop")) -> Convert
... A25: 400000 | B25: =MAX($B$5,A25*$B$4) -> 180000 | C25: =MIN(A25*'S-Corp Breakeven'!$B$12,'S-Corp Breakeven'!$B$11)*'S-Corp Breakeven'!$B$13+A25*'S-Corp Breakeven'!$B$12*'S-Corp Breakeven'!$B$14 -> 33590.6 | D25: =MIN(B25,'S-Corp Breakeven'!$B$11)*('S-Corp Breakeven'!$B$13+'S-Corp Breakeven'!$B$14)+MAX('S-Corp Breakeven'!$B$16,MAX(0,A25-B25-MIN(B25,'S-Corp Breakeven'!$B$11)*('S-Corp Breakeven'!$B$13+'S-Corp Breakeven'!$B$14)/2)*'S-Corp Breakeven'!$B$15)+'S-Corp Breakeven'!$B$7+'S-Corp Breakeven'!$B$8 -> 34233.45 | E25: =C25-D25 -> -642.85 | F25: =IF(E25>2000,"Convert",IF(E25>0,"Marginal","Stay sole prop")) -> Stay sole prop
A28: Educational tool only — not tax, legal, or investment advice. Verify all figures with your CPA. Lance Hulsey, CA Real Estate Broker, DRE# 01724888 · wealthbuildingbroker.com

Sheet Reasonable Comp
A1: Reasonable Compensation Worksheet
A2: Build a defensible W-2 salary from what you actually do. Bring this to your CPA.
A4: Role you perform | B4: Hours / week | C4: Market rate ($/hr) | D4: Annualized value | E4: Basis for market rate
A5: Sales / prospecting / showings | B5: 18 | C5: 38 | D5: =B5*C5*50 -> 34200 | E5: What a licensed showing/buyer's agent earns hourly in your market
A6: Transaction coordination & admin | B6: 8 | C6: 28 | D6: =B6*C6*50 -> 11200 | E6: Local TC hourly rate — check TC service pricing
A7: Marketing & content | B7: 5 | C7: 32 | D7: =B7*C7*50 -> 8000 | E7: Freelance marketing coordinator rate
A8: Business management & finance | B8: 4 | C8: 45 | D8: =B8*C8*50 -> 9000 | E8: Fractional ops/office manager rate
A9: Negotiation / contract work | B9: 5 | C9: 55 | D9: =B9*C9*50 -> 13750 | E9: Senior agent / broker-level work
A10: Total hours / implied salary | B10: =SUM(B5:B9) -> 40 | D10: =SUM(D5:D9) -> 76150 | E10: Assumes 50 working weeks — carries to nothing automatically; enter your chosen salary on the Breakeven sheet
A12: Cross-checks your CPA will want:
A13: · BLS median wage for CA real estate sales agents (search 'BLS OES 41-9022 California')
A14: · What brokerages pay licensed assistants and team salespeople in your county
A15: · RCReports or similar reasonable-comp study if income is $300K+ (the IRS uses these)
A16: Documentation beats theory: keep this worksheet with your corporate records, update annually.
A18: Educational tool only — not tax, legal, or investment advice. Verify all figures with your CPA. Lance Hulsey, CA Real Estate Broker, DRE# 01724888 · wealthbuildingbroker.com

Sheet CPA Checklist
A1: Before-You-Convert Checklist
A2: Answer what you can, ask your CPA the rest. Check items off as you go.
A4: THE MATH
A5: ☐ | B5: Is my net income consistently above the breakeven shown in this model — not just one good year?
A6: ☐ | B6: Run the S-corp math WITH the QBI deduction interaction. Does the savings hold after QBI?
A7: ☐ | B7: What reasonable comp will you defend for me, and what documentation do you want? (Bring the Reasonable Comp sheet.)
A8: THE MECHANICS
A9: ☐ | B9: LLC taxed as S-corp (Form 2553) or straight S-corp — which, and why? What's the filing deadline for my situation?
A10: ☐ | B10: Commissions must be paid to the entity: does my broker/state allow paying a licensed corporation? (CA: S-corp must hold a corporate license or use a licensed broker corporation — ask your broker of record.)
A11: ☐ | B11: Payroll setup: who runs it, what does it cost, and what's my filing calendar (941s, DE 9, W-2)?
A12: THE CALIFORNIA LAYER
A13: ☐ | B13: Confirm the 1.5% franchise tax / $800 minimum in my projection (first-year corp waiver?)
A14: ☐ | B14: If I'm an LLC now: is the LLC gross-receipts fee making the S-corp look better than it is?
A15: THE HOUSEKEEPING
A16: ☐ | B16: New EIN, business bank accounts, and commission re-papering — what breaks if I do this mid-year?
A17: ☐ | B17: Health insurance: how do I run owner premiums through payroll correctly (2% shareholder rules)?
A18: ☐ | B18: Retirement: Solo 401(k) or SEP — how does the employer contribution change once I have a W-2 salary?
A20: Educational tool only — not tax, legal, or investment advice. Verify all figures with your CPA. Lance Hulsey, CA Real Estate Broker, DRE# 01724888 · wealthbuildingbroker.com
